golocity/__init__.py
golocity/commands/__init__.py
golocity/commands/build.py
golocity/commands/deploy.py
golocity/helpers.py
golocity/image.py
golocity/main.py
golocity/py.typed
golocity/yagna.py
golocity-0.0.1.dist-info/entry_points.txt
golocity-0.0.1.dist-info/LICENSE
golocity-0.0.1.dist-info/WHEEL
golocity-0.0.1.dist-info/METADATA
golocity-0.0.1.dist-info/RECORD
