Metadata-Version: 2.1
Name: golocity
Version: 0.0.1
Summary: An easy to use execution manager for the Golem Network
Home-page: https://github.com/davidstyers/golocity
License: LGPL-3.0-or-later
Keywords: golem,cryptocurrency,computation,distributed
Author: davidstyers
Author-email: david@styers.dev
Requires-Python: >=3.9,<4.0
Classifier: License :: OSI Approved :: GNU Lesser General Public License v3 or later (LGPLv3+)
Classifier: Operating System :: OS Independent
Classifier: Programming Language :: Python :: 3
Classifier: Programming Language :: Python :: 3.9
Classifier: Topic :: System :: Distributed Computing
Requires-Dist: gvmkit-build (>=0.2.6,<0.3.0)
Requires-Dist: typer[all] (>=0.3.2,<0.4.0)
Requires-Dist: yapapi (>=0.6.1,<0.7.0)
Project-URL: Repository, https://github.com/davidstyers/golocity
